thankunext/__init__.py
thankunext/__main__.py
thankunext/thankunext.py
thankunext-0.0.3.dist-info/LICENSE
thankunext-0.0.3.dist-info/METADATA
thankunext-0.0.3.dist-info/WHEEL
thankunext-0.0.3.dist-info/entry_points.txt
thankunext-0.0.3.dist-info/RECORD
