Metadata-Version: 2.1
Name: thankunext
Version: 0.0.3
Summary: Python implementation of thankunext tool
License: MIT
Keywords: thankunext,nextjs urls
Author: cowsecurity
Author-email: yashsinghchauhanformal@gmail.com
Requires-Python: >=3.8,<4.0
Classifier: License :: OSI Approved :: MIT License
Classifier: Operating System :: OS Independent
Classifier: Programming Language :: Python :: 3
Classifier: Programming Language :: Python :: 3.8
Classifier: Programming Language :: Python :: 3.9
Classifier: Programming Language :: Python :: 3.10
Classifier: Programming Language :: Python :: 3.11
Classifier: Programming Language :: Python :: 3.12
Requires-Dist: requests (>=2.26.0)
Project-URL: Homepage, https://github.com/cowsecurity/thankunext
Project-URL: Issues, https://github.com/cowsecurity/thankunext/issues
